{
    "channels": [
        {
            "name": "CMS_WORKSHOP",
            "samples": [
                {
                    "data": [
                        230.11836338043213,
                        577.2832765579224,
                        590.7309322357178,
                        1038.2834119796753,
                        1377.6882591247559,
                        559.9818086624146,
                        304.3215856552124,
                        80.2280216217041,
                        31.35989475250244,
                        17.74839496612549
                    ],
                    "modifiers": [
                        {
                            "data": [
                                47.53179163943654,
                                99.7343655434124,
                                93.94338121925216,
                                104.06625933353313,
                                145.03108646503014,
                                86.09012699237948,
                                71.01948466525025,
                                18.91602536845152,
                                11.857096351486039,
                                8.876634475637744
                            ],
                            "name": "staterror_CMS_WORKSHOP",
                            "type": "staterror"
                        },
                        {
                            "data": null,
                            "name": "ttbar_norm",
                            "type": "normfactor"
                        },
                        {
                            "data": {
                                "hi": 0.16737492623468123,
                                "lo": 0.16646905768820522
                            },
                            "name": "MU_ID_SF",
                            "type": "normsys"
                        },
                        {
                            "data": {
                                "hi_data": [
                                    159.20604871416137,
                                    548.4618734672976,
                                    395.22734421330074,
                                    920.5821077503746,
                                    1179.6708959298821,
                                    896.8034807944158,
                                    336.03584487273844,
                                    224.31134924062354,
                                    88.4281715083954,
                                    59.01683244527359
                                ],
                                "lo_data": [
                                    159.2560648982979,
                                    548.5533480732281,
                                    395.2432550273187,
                                    920.4903126041187,
                                    1179.769671192043,
                                    896.7788239111791,
                                    335.8651949781007,
                                    224.32222988691413,
                                    88.44233304335833,
                                    59.02271532190477
                                ]
                            },
                            "name": "MU_ID_SF",
                            "type": "histosys"
                        },
                        {
                            "data": {
                                "hi": 0.2800683819512916,
                                "lo": 0.1787349135897774
                            },
                            "name": "PU_weight",
                            "type": "normsys"
                        },
                        {
                            "data": {
                                "hi_data": [
                                    171.2343626210374,
                                    517.4581752414589,
                                    382.0629299233763,
                                    953.4594382572458,
                                    1205.223580493419,
                                    899.8805528673787,
                                    326.32983965884034,
                                    198.33932844041396,
                                    116.34518631577191,
                                    37.41055511752089
                                ],
                                "lo_data": [
                                    157.0902829096963,
                                    550.0579073898033,
                                    406.86216230130174,
                                    935.1160879533558,
                                    1167.236444108571,
                                    876.7702015674631,
                                    359.18452176755295,
                                    215.73901133259702,
                                    82.57513999923368,
                                    57.11218960688708
                                ]
                            },
                            "name": "PU_weight",
                            "type": "histosys"
                        }
                    ],
                    "name": "ttbar_semilep"
                },
                {
                    "data": [
                        15.35419750213623,
                        0.0,
                        0.0,
                        25.094515800476074,
                        0.0,
                        0.0,
                        0.0,
                        6.746540546417236,
                        0.0,
                        0.0
                    ],
                    "modifiers": [
                        {
                            "data": [
                                15.35419750213623,
                                0.0,
                                0.0,
                                16.828198988932044,
                                0.0,
                                0.0,
                                0.0,
                                6.746540546417236,
                                0.0,
                                0.0
                            ],
                            "name": "staterror_CMS_WORKSHOP",
                            "type": "staterror"
                        },
                        {
                            "data": {
                                "hi": 0.10471855201495668,
                                "lo": 0.10415840306526011
                            },
                            "name": "MU_ID_SF",
                            "type": "normsys"
                        },
                        {
                            "data": {
                                "hi_data": [
                                    9.426457719107914,
                                    0.0,
                                    0.0,
                                    28.279373157323743,
                                    0.0,
                                    0.0,
                                    0.0,
                                    0.0,
                                    0.0,
                                    9.48942297259788
                                ],
                                "lo_data": [
                                    9.429175797095738,
                                    0.0,
                                    0.0,
                                    28.28752739128721,
                                    0.0,
                                    0.0,
                                    0.0,
                                    0.0,
                                    0.0,
                                    9.478550660646588
                                ]
                            },
                            "name": "MU_ID_SF",
                            "type": "histosys"
                        },
                        {
                            "data": {
                                "hi": 0.16850609986691115,
                                "lo": 0.13771459793001956
                            },
                            "name": "PU_weight",
                            "type": "normsys"
                        },
                        {
                            "data": {
                                "hi_data": [
                                    10.156802859669995,
                                    0.0,
                                    0.0,
                                    27.64479811366689,
                                    0.0,
                                    0.0,
                                    0.0,
                                    0.0,
                                    0.0,
                                    9.393652875692654
                                ],
                                "lo_data": [
                                    9.756866943665937,
                                    0.0,
                                    0.0,
                                    27.813531852953247,
                                    0.0,
                                    0.0,
                                    0.0,
                                    0.0,
                                    0.0,
                                    9.624855052410355
                                ]
                            },
                            "name": "PU_weight",
                            "type": "histosys"
                        }
                    ],
                    "name": "ttbar_had"
                },
                {
                    "data": [
                        73.8757838010788,
                        72.1206283569336,
                        85.5974851846695,
                        89.06983292102814,
                        74.86011719703674,
                        56.736878991127014,
                        40.798065423965454,
                        13.66655707359314,
                        5.22042715549469,
                        0.0
                    ],
                    "modifiers": [
                        {
                            "data": [
                                16.00145069765131,
                                15.203491531093679,
                                15.71384506383061,
                                17.03892998881091,
                                15.148518316244152,
                                13.17091075858624,
                                12.035017758127966,
                                6.258859779959666,
                                3.792635457866155,
                                0.0
                            ],
                            "name": "staterror_CMS_WORKSHOP",
                            "type": "staterror"
                        },
                        {
                            "data": {
                                "hi": 0.3490811142627224,
                                "lo": 0.34716483963395195
                            },
                            "name": "MU_ID_SF",
                            "type": "normsys"
                        },
                        {
                            "data": {
                                "hi_data": [
                                    48.05366160538932,
                                    79.1789536094283,
                                    76.4674721645776,
                                    79.22054973225326,
                                    73.52593090533662,
                                    56.53808587454869,
                                    36.783822881568575,
                                    28.28089175340095,
                                    28.221956698126917,
                                    5.674450880296843
                                ],
                                "lo_data": [
                                    48.075333487936646,
                                    79.20075457415787,
                                    76.46581028695574,
                                    79.23315082758039,
                                    73.48967329160718,
                                    56.55119162077854,
                                    36.78858197920167,
                                    28.23130428922295,
                                    28.23717030005171,
                                    5.672805447434502
                                ]
                            },
                            "name": "MU_ID_SF",
                            "type": "histosys"
                        },
                        {
                            "data": {
                                "hi": 0.5744546880766846,
                                "lo": 0.3564541882073397
                            },
                            "name": "PU_weight",
                            "type": "normsys"
                        },
                        {
                            "data": {
                                "hi_data": [
                                    52.73249879259421,
                                    80.14445136093022,
                                    75.78228156683792,
                                    63.674860517198006,
                                    82.27972539278626,
                                    72.35848812497642,
                                    27.960870882470157,
                                    30.6861149209478,
                                    25.23116083520676,
                                    1.0953237109792966
                                ],
                                "lo_data": [
                                    49.762089649762565,
                                    75.53726500432131,
                                    83.25671310911005,
                                    78.94164561705148,
                                    70.12215543890088,
                                    57.636681929120684,
                                    35.52370238600743,
                                    26.981432119011863,
                                    31.500609927677576,
                                    2.6834809239632182
                                ]
                            },
                            "name": "PU_weight",
                            "type": "histosys"
                        }
                    ],
                    "name": "ttbar_lep"
                },
                {
                    "data": [
                        0.15786930872127414,
                        0.18827098468318582,
                        0.35274446476250887,
                        1.6105565666221082,
                        2.745610071811825,
                        4.6000657002441585,
                        4.429402180947363,
                        3.043985318392515,
                        1.4747157911770046,
                        0.33645893167704344
                    ],
                    "modifiers": [
                        {
                            "data": [
                                0.052891330207478396,
                                0.05315593934532163,
                                0.054834653167895035,
                                0.17501219537623428,
                                0.17083999946802847,
                                0.26079133545685906,
                                0.26042645134830034,
                                0.2249490359506885,
                                0.17471755660551863,
                                0.05494341828329197
                            ],
                            "name": "staterror_CMS_WORKSHOP",
                            "type": "staterror"
                        },
                        {
                            "data": null,
                            "name": "zprime_norm",
                            "type": "normfactor"
                        },
                        {
                            "data": {
                                "hi": 743.66225886,
                                "lo": 739.5927528674124
                            },
                            "name": "MU_ID_SF",
                            "type": "normsys"
                        },
                        {
                            "data": {
                                "hi_data": [
                                    0.1287213667407069,
                                    0.17383900555877635,
                                    0.31065215306208327,
                                    0.88689361885039,
                                    2.22916719737858,
                                    3.5318881606353383,
                                    4.28673599115825,
                                    3.656115990571345,
                                    2.474475889113136,
                                    1.261189945970383
                                ],
                                "lo_data": [
                                    0.1287749296624321,
                                    0.17388220402741655,
                                    0.3106773254061502,
                                    0.8868461961032025,
                                    2.2289270473389404,
                                    3.531593508235276,
                                    4.2866170205754415,
                                    3.6562019680786584,
                                    2.474808505464753,
                                    1.2613506141467148
                                ]
                            },
                            "name": "MU_ID_SF",
                            "type": "histosys"
                        },
                        {
                            "data": {
                                "hi": 1351.993648759587,
                                "lo": 794.4595730027
                            },
                            "name": "PU_weight",
                            "type": "normsys"
                        },
                        {
                            "data": {
                                "hi_data": [
                                    0.12494643454341776,
                                    0.19486051001250695,
                                    0.34628389778661356,
                                    0.8734053417905084,
                                    2.292943607690541,
                                    3.618419753813041,
                                    4.255756887464098,
                                    3.6057976025422427,
                                    2.443518277955159,
                                    1.1837470054408588
                                ],
                                "lo_data": [
                                    0.1302636269588035,
                                    0.1814198315179637,
                                    0.3105597263805214,
                                    0.901239171072974,
                                    2.220425856414321,
                                    3.5137793768187504,
                                    4.293770369490358,
                                    3.660765682025903,
                                    2.4713147158045943,
                                    1.2561409625548023
                                ]
                            },
                            "name": "PU_weight",
                            "type": "histosys"
                        }
                    ],
                    "name": "signal"
                },
                {
                    "data": [
                        4.1889848846476525,
                        5.819510309025645,
                        6.887039378751069,
                        33.68881237367168,
                        5.62917237309739,
                        10.95538502628915,
                        4.354577488498762,
                        3.9780023039784282,
                        0.07536423089914024,
                        1.6386872322764248
                    ],
                    "modifiers": [
                        {
                            "data": [
                                3.158582387720984,
                                3.1885409033271674,
                                3.4999221693322453,
                                26.855461921061035,
                                3.9931236789885785,
                                4.9338351998720995,
                                3.1602203216460922,
                                3.154011300862165,
                                0.07174449680634912,
                                1.4740196881524001
                            ],
                            "name": "staterror_CMS_WORKSHOP",
                            "type": "staterror"
                        },
                        {
                            "data": {
                                "hi": 2.864536564478993,
                                "lo": 2.8478920267058223
                            },
                            "name": "MU_ID_SF",
                            "type": "normsys"
                        },
                        {
                            "data": {
                                "hi_data": [
                                    3.446019908475953,
                                    9.647710343911005,
                                    11.735079755177702,
                                    14.134346288039064,
                                    9.993212179259332,
                                    10.343288513937447,
                                    7.232887637886414,
                                    4.817719984974246,
                                    3.788451788660781,
                                    2.076819200813408
                                ],
                                "lo_data": [
                                    3.448613514969273,
                                    9.651887906377768,
                                    11.737697527507654,
                                    14.129087281316773,
                                    9.99041131150741,
                                    10.347368928002986,
                                    7.223158998374797,
                                    4.820606374983438,
                                    3.7903123318098073,
                                    2.076391426285444
                                ]
                            },
                            "name": "MU_ID_SF",
                            "type": "histosys"
                        },
                        {
                            "data": {
                                "hi": 7.142683311405925,
                                "lo": 2.9701134663459907
                            },
                            "name": "PU_weight",
                            "type": "normsys"
                        },
                        {
                            "data": {
                                "hi_data": [
                                    2.426516465181906,
                                    7.426294301967295,
                                    14.409740342187094,
                                    14.416546804456909,
                                    11.252735806353751,
                                    8.930011291739858,
                                    7.1231924421623365,
                                    5.698589976072909,
                                    3.331937275357444,
                                    2.199970895655839
                                ],
                                "lo_data": [
                                    3.561986349543844,
                                    9.599185265163422,
                                    11.85895900881652,
                                    12.99877445064238,
                                    9.032392205783482,
                                    11.060419479404286,
                                    7.92064935879,
                                    4.692985923391144,
                                    4.288348005373872,
                                    2.201835554226393
                                ]
                            },
                            "name": "PU_weight",
                            "type": "histosys"
                        }
                    ],
                    "name": "wjets"
                }
            ]
        }
    ],
    "measurements": [
        {
            "config": {
                "parameters": [
                    {
                        "bounds": [
                            [
                                0,
                                10
                            ]
                        ],
                        "inits": [
                            1.0
                        ],
                        "name": "zprime_norm"
                    },
                    {
                        "bounds": [
                            [
                                0,
                                10
                            ]
                        ],
                        "inits": [
                            1.0
                        ],
                        "name": "ttbar_norm"
                    }
                ],
                "poi": "zprime_norm"
            },
            "name": "CMS_Zprime"
        }
    ],
    "observations": [
        {
            "data": [
                3.0,
                8.0,
                16.0,
                18.0,
                25.0,
                14.0,
                4.0,
                1.0,
                1.0,
                0.0
            ],
            "name": "CMS_WORKSHOP"
        }
    ],
    "version": "1.0.0"
}